{"vendor":"zulu","filename":"zulu21.48.17-ca-jre21.0.10-linux_musl_x64.tar.gz","release_type":"ga","version":"21.48.17","java_version":"21.0.10","jvm_impl":"hotspot","os":"linux","architecture":"x86_64","file_type":"tar.gz","image_type":"jre","features":["musl"],"url":"https://static.azul.com/zulu/bin/zulu21.48.17-ca-jre21.0.10-linux_musl_x64.tar.gz","md5":"4b552330f8fc67bbbe71062c2ca0c9c1","md5_file":"zulu21.48.17-ca-jre21.0.10-linux_musl_x64.tar.gz.md5","sha1":"146b3694953b9d789c4fcaf3fe3d4ee02672066f","sha1_file":"zulu21.48.17-ca-jre21.0.10-linux_musl_x64.tar.gz.sha1","sha256":"010f1b950a5e9d50d6c2cb5a33680e0fbc1de9718a7a38c412f741ec4146ab42","sha256_file":"zulu21.48.17-ca-jre21.0.10-linux_musl_x64.tar.gz.sha256","sha512":"0838e93779641a4750f1f9e6b86cda14d453f7be1ce8cd5c04ca2d56c1efa0aded8f207f77c64e49de236ef3f2e1003bf91db2b0719fde01444fecabe0f2c053","sha512_file":"zulu21.48.17-ca-jre21.0.10-linux_musl_x64.tar.gz.sha512","size":53314086}
