{"vendor":"zulu","filename":"zulu8.90.0.19-ca-jre8.0.472-macosx_aarch64.zip","release_type":"ga","version":"8.90.0.19","java_version":"8.0.472","jvm_impl":"hotspot","os":"macosx","architecture":"aarch64","file_type":"zip","image_type":"jre","features":[],"url":"https://static.azul.com/zulu/bin/zulu8.90.0.19-ca-jre8.0.472-macosx_aarch64.zip","md5":"d3c28b03139994275be0132dd709d357","md5_file":"zulu8.90.0.19-ca-jre8.0.472-macosx_aarch64.zip.md5","sha1":"b58b33f044b33b0f9f77d9e7961d35890511da68","sha1_file":"zulu8.90.0.19-ca-jre8.0.472-macosx_aarch64.zip.sha1","sha256":"00153fbda20fec9bfeefd575ad57209649c6a9cc6f53986a3091925e6a057854","sha256_file":"zulu8.90.0.19-ca-jre8.0.472-macosx_aarch64.zip.sha256","sha512":"e4a4b8bfc09ed196b34fb16bddc8d4c80fde6251fc06d5dd0267fec7de4bf4ccb08a893b56a9a75f70caceb4517d6301b59ad93c519712ceb4e22f6a8cbf3f43","sha512_file":"zulu8.90.0.19-ca-jre8.0.472-macosx_aarch64.zip.sha512","size":41294735}
