{"vendor":"zulu","filename":"zulu17.64.17-ca-fx-jre17.0.18-macosx_aarch64.tar.gz","release_type":"ga","version":"17.64.17","java_version":"17.0.18","jvm_impl":"hotspot","os":"macosx","architecture":"aarch64","file_type":"tar.gz","image_type":"jre","features":["javafx"],"url":"https://static.azul.com/zulu/bin/zulu17.64.17-ca-fx-jre17.0.18-macosx_aarch64.tar.gz","md5":"0bc4ae9606817a02f85d62cd31791b83","md5_file":"zulu17.64.17-ca-fx-jre17.0.18-macosx_aarch64.tar.gz.md5","sha1":"151d51c68cc39a4bc6bb63f57478845f36281ab3","sha1_file":"zulu17.64.17-ca-fx-jre17.0.18-macosx_aarch64.tar.gz.sha1","sha256":"ec18d306676cb9abbdc65f9b87d5bb09cf72e1876088fa432029351f24b44508","sha256_file":"zulu17.64.17-ca-fx-jre17.0.18-macosx_aarch64.tar.gz.sha256","sha512":"9be833e57d67a9551031d435b2284da225ac852dad7617a96ad3393e3c35be5a7fbd1d13f7fa9d986845a64bb199df9fddaefcfbd7167e49664a0fe131cd2b56","sha512_file":"zulu17.64.17-ca-fx-jre17.0.18-macosx_aarch64.tar.gz.sha512","size":84251211}
