{
  "architecture": "x86_64",
  "distro": "zulu",
  "features": [
    "musl"
  ],
  "file_type": "tar.gz",
  "filename": "zulu13.31.11-ca-jre13.0.3-linux_musl_x64.tar.gz",
  "image_type": "jre",
  "java_version": "13.0.3",
  "jvm_impl": "hotspot",
  "md5": "9c647b35ac25dd6f87d6cb3b5b61c25c",
  "os": "linux",
  "release_info": {
    "IMPLEMENTOR": "Azul Systems, Inc.",
    "IMPLEMENTOR_VERSION": "Zulu13.31+11-CA",
    "JAVA_VERSION": "13.0.3",
    "JAVA_VERSION_DATE": "2020-04-14",
    "LIBC": "musl",
    "MODULES": "java.base java.compiler java.datatransfer java.xml java.prefs java.desktop java.instrument java.logging java.management java.security.sasl java.naming java.rmi java.management.rmi java.net.http java.scripting java.security.jgss java.transaction.xa java.sql java.sql.rowset java.xml.crypto java.se java.smartcardio jdk.accessibility jdk.internal.vm.ci jdk.management jdk.unsupported jdk.internal.vm.compiler jdk.aot jdk.charsets jdk.crypto.ec jdk.crypto.cryptoki jdk.dynalink jdk.httpserver jdk.internal.ed jdk.internal.le jdk.internal.vm.compiler.management jdk.jdwp.agent jdk.jfr jdk.jsobject jdk.localedata jdk.management.agent jdk.management.jfr jdk.naming.dns jdk.naming.rmi jdk.net jdk.pack jdk.scripting.nashorn jdk.scripting.nashorn.shell jdk.sctp jdk.security.auth jdk.security.jgss jdk.xml.dom jdk.zipfs",
    "OS_ARCH": "x86_64",
    "OS_NAME": "Linux",
    "SOURCE": ".:hg:1059b20b3fc2"
  },
  "release_type": "ga",
  "sha1": "48d3d9bd482acb6a07005587d60be5caf8bfe5ec",
  "sha256": "24d47cdb5c7e289953ec853b9c1ecd091f459bbd03259f3a2448909978f04151",
  "sha512": "b8381d6c4099916eb3be955356f82427343d43675948e514b1ecda02f20ffd3823df0901d65d200620686fa462da235774a4bd274338ab1e79d9b5eb45de26c8",
  "size": 46291929,
  "url": "https://static.azul.com/zulu/bin/zulu13.31.11-ca-jre13.0.3-linux_musl_x64.tar.gz",
  "vendor": "azul",
  "version": "13.31.11"
}