{"vendor":"zulu","filename":"zulu25.32.21-ca-fx-jdk25.0.2-macosx_x64.dmg","release_type":"ga","version":"25.32.21","java_version":"25.0.2","jvm_impl":"hotspot","os":"macosx","architecture":"x86_64","file_type":"dmg","image_type":"jdk","features":["javafx"],"url":"https://static.azul.com/zulu/bin/zulu25.32.21-ca-fx-jdk25.0.2-macosx_x64.dmg","md5":"86398801e056c7fe5c90f061dcf55c1f","md5_file":"zulu25.32.21-ca-fx-jdk25.0.2-macosx_x64.dmg.md5","sha1":"54ac9a8867e4b9d6d6772e056e69fdb1986a8ac2","sha1_file":"zulu25.32.21-ca-fx-jdk25.0.2-macosx_x64.dmg.sha1","sha256":"2d37fd30cb8ed914d4907b5a305b3b1ac9384ff2be8aa3b258614188c5dc79a4","sha256_file":"zulu25.32.21-ca-fx-jdk25.0.2-macosx_x64.dmg.sha256","sha512":"bf45a06fe9bf231f239a21efe0d2b6c59fd69fa2fa9d40b5c57497d11b7528bc34ea92cc810500e6de2978e715848ed25a64fd88e7a897cffc5ffd2016f3da92","sha512_file":"zulu25.32.21-ca-fx-jdk25.0.2-macosx_x64.dmg.sha512","size":332452704}
