{
  "architecture": "x86_64",
  "distro": "zulu",
  "features": [
    "javafx"
  ],
  "file_type": "tar.gz",
  "filename": "zulu16.32.15-ca-fx-jdk16.0.2-macosx_x64.tar.gz",
  "image_type": "jdk",
  "java_version": "16.0.2",
  "jvm_impl": "hotspot",
  "md5": "f996b89712a167aad0f3746a5c1080ab",
  "os": "macosx",
  "release_info": {
    "IMPLEMENTOR": "Azul Systems, Inc.",
    "IMPLEMENTOR_VERSION": "Zulu16.32+15-CA",
    "JAVA_VERSION": "16.0.2",
    "JAVA_VERSION_DATE": "2021-07-20",
    "LIBC": "default",
    "MODULES": "java.base java.compiler java.datatransfer java.xml java.prefs java.desktop java.instrument java.logging java.management java.security.sasl java.naming java.rmi java.management.rmi java.net.http java.scripting java.security.jgss java.transaction.xa java.sql java.sql.rowset java.xml.crypto java.se java.smartcardio jdk.jfr javafx.base jdk.unsupported javafx.graphics javafx.controls javafx.fxml javafx.media jdk.unsupported.desktop javafx.swing jdk.jsobject jdk.xml.dom javafx.web jdk.accessibility jdk.internal.vm.ci jdk.management jdk.internal.vm.compiler jdk.aot jdk.internal.jvmstat jdk.attach jdk.charsets jdk.compiler jdk.crypto.ec jdk.crypto.cryptoki jdk.dynalink jdk.internal.ed jdk.editpad jdk.hotspot.agent jdk.httpserver jdk.incubator.foreign jdk.incubator.vector jdk.internal.le jdk.internal.opt jdk.internal.vm.compiler.management jdk.jartool jdk.javadoc jdk.jcmd jdk.management.agent jdk.jconsole jdk.jdeps jdk.jdwp.agent jdk.jdi jdk.jlink jdk.jpackage jdk.jshell jdk.jstatd jdk.localedata jdk.management.jfr jdk.naming.dns jdk.naming.rmi jdk.net jdk.nio.mapmode jdk.sctp jdk.security.auth jdk.security.jgss jdk.zipfs",
    "OS_ARCH": "x86_64",
    "OS_NAME": "Darwin",
    "SOURCE": ".:git:4bbb066da06d"
  },
  "release_type": "ga",
  "sha1": "bbfdf20df5137b3b05027eff895146ef78d6d88b",
  "sha256": "e9445a4813474162dab8efff902b8a5dbe19ec0ab2b215a7a1e244c9544a81a6",
  "sha512": "e786c25cbe8f94fcf2744f13090909620acb1e4ff5f4960cb487c9816a951549949899391770f62726660df732252d96a3d06eb76dc2778fe747bb13694d675c",
  "size": 289942403,
  "url": "https://static.azul.com/zulu/bin/zulu16.32.15-ca-fx-jdk16.0.2-macosx_x64.tar.gz",
  "vendor": "azul",
  "version": "16.32.15"
}