{
  "architecture": "i686",
  "distro": "liberica",
  "features": [
    "libericafx",
    "minimal-vm",
    "javafx"
  ],
  "file_type": "zip",
  "filename": "bellsoft-jre11.0.6+10-windows-i586-full.zip",
  "image_type": "jre",
  "java_version": "11.0.6+10",
  "jvm_impl": "hotspot",
  "md5": "3ba7a44956f405c00ba103a187dc8f63",
  "os": "windows",
  "release_info": {
    "IMPLEMENTOR": "BellSoft",
    "JAVA_VERSION": "11.0.6",
    "JAVA_VERSION_DATE": "2020-01-15",
    "MODULES": "java.base java.compiler java.datatransfer java.xml java.prefs java.desktop java.instrument java.logging java.management java.security.sasl java.naming java.rmi java.management.rmi java.net.http java.scripting java.security.jgss java.transaction.xa java.sql java.sql.rowset java.xml.crypto java.se java.smartcardio javafx.base jdk.unsupported javafx.graphics javafx.controls javafx.fxml javafx.media javafx.swing jdk.jsobject jdk.xml.dom javafx.web jdk.accessibility jdk.charsets jdk.crypto.ec jdk.crypto.cryptoki jdk.crypto.mscapi jdk.dynalink jdk.httpserver jdk.internal.ed jdk.internal.le jdk.jdwp.agent jdk.jfr jdk.localedata jdk.management jdk.management.agent jdk.management.jfr jdk.naming.dns jdk.naming.rmi jdk.net jdk.pack jdk.scripting.nashorn jdk.scripting.nashorn.shell jdk.sctp jdk.security.auth jdk.security.jgss jdk.zipfs",
    "OS_ARCH": "x86",
    "OS_NAME": "Windows",
    "SOURCE": ".:hg:92ad8373cf4d+"
  },
  "release_type": "ga",
  "sha1": "95a46f42dc7ce1b2d6ecb380cff4d59bdc090b52",
  "sha256": "a1a91b687cbcfcd838c6b502a90e0592ec7c9fff889458a849f5dc7dd9c21425",
  "sha512": "e9182b409607a4f2e26e806377f3a8320966fd0cf3ee8fae3ab8e850576e0ab9cfb4a4a3672f9689a500fbdbe94dc7ba7236a4941a72d663c48adb58f36f4101",
  "size": 62801950,
  "url": "https://github.com/bell-sw/Liberica/releases/download/11.0.6+10/bellsoft-jre11.0.6+10-windows-i586-full.zip",
  "vendor": "bellsoft",
  "version": "11.0.6+10"
}