{
"architecture": "aarch64",
"distro": "liberica",
"features": [
  "lite"
],
"file_type": "tar.gz",
"filename": "bellsoft-jdk25.0.1+11-macos-aarch64-lite.tar.gz",
"image_type": "jdk",
"java_version": "25.0.1+11",
"jvm_impl": "hotspot",
"md5": "8fac1781d0d75b82961dc6c9a3f284fe",
"os": "macosx",
"release_info": {
  "IMPLEMENTOR": "BellSoft",
  "JAVA_RUNTIME_VERSION": "25.0.1+11-LTS",
  "JAVA_VERSION": "25.0.1",
  "JAVA_VERSION_DATE": "2025-10-21",
  "LIBC": "default",
  "MODULES": "java.base java.compiler java.datatransfer java.xml java.prefs java.desktop java.instrument java.logging java.management java.security.sasl java.naming java.rmi java.management.rmi java.net.http java.scripting java.security.jgss java.transaction.xa java.sql java.sql.rowset java.xml.crypto java.se java.smartcardio jdk.accessibility jdk.internal.jvmstat jdk.attach jdk.charsets jdk.internal.opt jdk.zipfs jdk.compiler jdk.crypto.cryptoki jdk.crypto.ec jdk.dynalink jdk.internal.ed jdk.editpad jdk.internal.vm.ci jdk.graal.compiler jdk.graal.compiler.management jdk.hotspot.agent jdk.httpserver jdk.incubator.vector jdk.internal.le jdk.internal.md jdk.jartool jdk.javadoc jdk.jcmd jdk.management jdk.management.agent jdk.jconsole jdk.jdeps jdk.jdwp.agent jdk.jdi jdk.jfr jdk.jlink jdk.jpackage jdk.jshell jdk.jsobject jdk.jstatd jdk.localedata jdk.management.jfr jdk.naming.dns jdk.naming.rmi jdk.net jdk.nio.mapmode jdk.sctp jdk.security.auth jdk.security.jgss jdk.unsupported jdk.unsupported.desktop jdk.xml.dom",
  "OS_ARCH": "aarch64",
  "OS_NAME": "Darwin",
  "SOURCE": ".:git:efa46d04910a+"
},
"release_type": "ga",
"sha1": "b1317ef08e3917055bae50286120de68378cae86",
"sha256": "7eb17cbe5588379f68b27636ba4d92a54b09cba9207c56fc2b2f26fcf50dde87",
"sha512": "ea8be153b52b5c38b377ce784a7ac876052ae8132601f12c1b84321002687c27a318d6721dea80da6f630aa0329893b9917c5493fb6a6b06ab0ae3f13798e966",
"size": 80580389,
"url": "https://github.com/bell-sw/Liberica/releases/download/25.0.1+11/bellsoft-jdk25.0.1+11-macos-aarch64-lite.tar.gz",
"vendor": "bellsoft",
"version": "25.0.1+11"
}