{
  "architecture": "aarch64",
  "distro": "liberica",
  "features": [
    "lite"
  ],
  "file_type": "tar.gz",
  "filename": "bellsoft-jdk11.0.8+10-linux-aarch64-lite.tar.gz",
  "image_type": "jdk",
  "java_version": "11.0.8+10",
  "jvm_impl": "hotspot",
  "md5": "5555bf1511bcb2ca0ba6b60cc61670a7",
  "os": "linux",
  "release_info": {
    "IMPLEMENTOR": "BellSoft",
    "JAVA_VERSION": "11.0.8",
    "JAVA_VERSION_DATE": "2020-07-14",
    "MODULES": "java.base java.compiler java.datatransfer java.xml java.prefs java.desktop java.instrument java.logging java.management java.security.sasl java.naming java.rmi java.management.rmi java.net.http java.scripting java.security.jgss java.transaction.xa java.sql java.sql.rowset java.xml.crypto java.se java.smartcardio jdk.accessibility jdk.internal.vm.ci jdk.management jdk.unsupported jdk.internal.vm.compiler jdk.aot jdk.internal.jvmstat jdk.attach jdk.charsets jdk.compiler jdk.crypto.ec jdk.crypto.cryptoki jdk.dynalink jdk.internal.ed jdk.editpad jdk.hotspot.agent jdk.httpserver jdk.internal.le jdk.internal.opt jdk.internal.vm.compiler.management jdk.jartool jdk.javadoc jdk.jcmd jdk.management.agent jdk.jconsole jdk.jdeps jdk.jdwp.agent jdk.jdi jdk.jfr jdk.jlink jdk.jshell jdk.jsobject jdk.jstatd jdk.localedata jdk.management.jfr jdk.naming.dns jdk.naming.rmi jdk.net jdk.pack jdk.rmic jdk.scripting.nashorn jdk.scripting.nashorn.shell jdk.sctp jdk.security.auth jdk.security.jgss jdk.unsupported.desktop jdk.xml.dom jdk.zipfs",
    "OS_ARCH": "aarch64",
    "OS_NAME": "Linux",
    "SOURCE": ".:hg:030bc020dc04+"
  },
  "release_type": "ga",
  "sha1": "e5018fcb5456d1eeccac8308b5a9d7ef437ecce0",
  "sha256": "a80c7180becca186e4a394f95394fa29a4ca8ff9ab55434716c9718dddb38f63",
  "sha512": "8e0be26e8856b0f7d136178db16520319443343ec79821863673b41bc27981c44185de02e63070f46093bd005c1b2963f07364de67600ec1476962d5ec9bcfd8",
  "size": 73876685,
  "url": "https://github.com/bell-sw/Liberica/releases/download/11.0.8+10/bellsoft-jdk11.0.8+10-linux-aarch64-lite.tar.gz",
  "vendor": "bellsoft",
  "version": "11.0.8+10"
}