{
  "architecture": "i686",
  "distro": "liberica",
  "features": [],
  "file_type": "rpm",
  "filename": "bellsoft-jre17.0.9+11-linux-i586.rpm",
  "image_type": "jre",
  "java_version": "17.0.9+11",
  "jvm_impl": "hotspot",
  "md5": "4ea93b4982fcb6fbd08b2dab9ff911ea",
  "os": "linux",
  "release_info": {
    "IMPLEMENTOR": "BellSoft",
    "JAVA_RUNTIME_VERSION": "17.0.9+11-LTS",
    "JAVA_VERSION": "17.0.9",
    "JAVA_VERSION_DATE": "2023-10-17",
    "LIBC": "gnu",
    "MODULES": "java.base java.compiler java.datatransfer java.xml java.prefs java.desktop java.instrument java.logging java.management java.security.sasl java.naming java.rmi java.management.rmi java.net.http java.scripting java.security.jgss java.transaction.xa java.sql java.sql.rowset java.xml.crypto java.se java.smartcardio jdk.accessibility jdk.charsets jdk.crypto.ec jdk.crypto.cryptoki jdk.dynalink jdk.httpserver jdk.incubator.foreign jdk.incubator.vector jdk.jdwp.agent jdk.jfr jdk.jsobject jdk.localedata jdk.management jdk.management.agent jdk.management.jfr jdk.naming.dns jdk.naming.rmi jdk.net jdk.nio.mapmode jdk.sctp jdk.security.auth jdk.security.jgss jdk.unsupported jdk.xml.dom jdk.zipfs",
    "OS_ARCH": "x86",
    "OS_NAME": "Linux",
    "SOURCE": ".:git:6862c12c2e37+"
  },
  "release_type": "ga",
  "sha1": "8a54e49e09cac351409107f542310dba77463fbe",
  "sha256": "647b1136d253617894ac236dea90c493f63baebdf966e6e3b3297b4d0ce6eac7",
  "sha512": "52c18e8e9f4ae58ea8bcf974ecbcdc99e015b47e45ae9f8ae5bfa5bcbb631ab2797ab15cdafab1b3431306f3cc6f851c4107e2b8c2224c14ad8a694c019a371b",
  "size": 33487560,
  "url": "https://github.com/bell-sw/Liberica/releases/download/17.0.9+11/bellsoft-jre17.0.9+11-linux-i586.rpm",
  "vendor": "bellsoft",
  "version": "17.0.9+11"
}