{
  "architecture": "x86_64",
  "distro": "liberica",
  "features": [
    "libericafx",
    "minimal-vm",
    "javafx"
  ],
  "file_type": "msi",
  "filename": "bellsoft-jdk19.0.1+11-windows-amd64-full.msi",
  "image_type": "jdk",
  "java_version": "19.0.1+11",
  "jvm_impl": "hotspot",
  "md5": "7faa4cd2386d0435a31de88ecd45736a",
  "os": "windows",
  "release_info": {
    "IMPLEMENTOR": "BellSoft",
    "JAVA_VERSION": "19.0.1",
    "JAVA_VERSION_DATE": "2022-10-18",
    "LIBC": "default",
    "MODULES": "java.base java.compiler java.datatransfer java.xml java.prefs java.desktop java.instrument java.logging java.management java.security.sasl java.naming java.rmi java.management.rmi java.net.http java.scripting java.security.jgss java.transaction.xa java.sql java.sql.rowset java.xml.crypto java.se java.smartcardio jdk.jfr javafx.base jdk.unsupported javafx.graphics javafx.controls javafx.fxml javafx.media jdk.unsupported.desktop javafx.swing jdk.jsobject jdk.xml.dom javafx.web jdk.accessibility jdk.internal.jvmstat jdk.attach jdk.charsets jdk.zipfs jdk.compiler jdk.crypto.ec jdk.crypto.cryptoki jdk.crypto.mscapi jdk.dynalink jdk.internal.ed jdk.editpad jdk.hotspot.agent jdk.httpserver jdk.incubator.concurrent jdk.incubator.vector jdk.internal.le jdk.internal.opt jdk.internal.vm.ci jdk.internal.vm.compiler jdk.internal.vm.compiler.management jdk.jartool jdk.javadoc jdk.jcmd jdk.management jdk.management.agent jdk.jconsole jdk.jdeps jdk.jdwp.agent jdk.jdi jdk.jlink jdk.jpackage jdk.jshell jdk.jstatd jdk.localedata jdk.management.jfr jdk.naming.dns jdk.naming.rmi jdk.net jdk.nio.mapmode jdk.random jdk.sctp jdk.security.auth jdk.security.jgss",
    "OS_ARCH": "x86_64",
    "OS_NAME": "Windows",
    "SOURCE": ".:git:910874d9a8af+"
  },
  "release_type": "ga",
  "sha1": "fd5ac1f960b7e3314da8fbc67cbb1adbfa1d1695",
  "sha256": "e5f5c5f067d41aaac97d52837322117c211bf00c3565ab0dbb0ad1a4e504c156",
  "sha512": "288cfe67c119a307231a14e8f56ef44b175251d326f46a2fe9e7161d216ba62ddc2ebbfbd007a0a630749f0f536e240a0023b7b46c71a86e49d0a198c1aee087",
  "size": 275415040,
  "url": "https://github.com/bell-sw/Liberica/releases/download/19.0.1+11/bellsoft-jdk19.0.1+11-windows-amd64-full.msi",
  "vendor": "bellsoft",
  "version": "19.0.1+11"
}