{
  "architecture": "i686",
  "distro": "liberica",
  "features": [],
  "file_type": "deb",
  "filename": "bellsoft-jdk17.0.9+11-linux-i586.deb",
  "image_type": "jdk",
  "java_version": "17.0.9+11",
  "jvm_impl": "hotspot",
  "md5": "4e4b3f6797b0b9b768a04f4fb1b6fbcf",
  "os": "linux",
  "release_info": {
    "IMPLEMENTOR": "BellSoft",
    "JAVA_RUNTIME_VERSION": "17.0.9+11-LTS",
    "JAVA_VERSION": "17.0.9",
    "JAVA_VERSION_DATE": "2023-10-17",
    "LIBC": "gnu",
    "MODULES": "java.base java.compiler java.datatransfer java.xml java.prefs java.desktop java.instrument java.logging java.management java.security.sasl java.naming java.rmi java.management.rmi java.net.http java.scripting java.security.jgss java.transaction.xa java.sql java.sql.rowset java.xml.crypto java.se java.smartcardio jdk.accessibility jdk.internal.jvmstat jdk.attach jdk.charsets jdk.compiler jdk.crypto.ec jdk.crypto.cryptoki jdk.dynalink jdk.internal.ed jdk.editpad jdk.hotspot.agent jdk.httpserver jdk.incubator.foreign jdk.incubator.vector jdk.internal.le jdk.internal.opt jdk.jartool jdk.javadoc jdk.jcmd jdk.management jdk.management.agent jdk.jconsole jdk.jdeps jdk.jdwp.agent jdk.jdi jdk.jfr jdk.jlink jdk.jpackage jdk.jshell jdk.jsobject jdk.jstatd jdk.localedata jdk.management.jfr jdk.naming.dns jdk.naming.rmi jdk.net jdk.nio.mapmode jdk.random jdk.sctp jdk.security.auth jdk.security.jgss jdk.unsupported jdk.unsupported.desktop jdk.xml.dom jdk.zipfs",
    "OS_ARCH": "x86",
    "OS_NAME": "Linux",
    "SOURCE": ".:git:6862c12c2e37+"
  },
  "release_type": "ga",
  "sha1": "41342eb9b4468b9c0c04f534b4cdd389ef942244",
  "sha256": "6d63a3de6e8b1504c8048dc17f7b431df20a9c42ac195e96f83d6a57de5c5351",
  "sha512": "fadca244c9a1dc4e0bc77d10972159d75bb1ddec3ee732870bf14c23ed4a93596d78427759f3415d093545650805b25bfeaca6b1fb37e307fcf1c68533d3965e",
  "size": 170700372,
  "url": "https://github.com/bell-sw/Liberica/releases/download/17.0.9+11/bellsoft-jdk17.0.9+11-linux-i586.deb",
  "vendor": "bellsoft",
  "version": "17.0.9+11"
}