{
  "architecture": "aarch64",
  "distro": "sapmachine",
  "features": null,
  "file_type": "tar.gz",
  "filename": "sapmachine-jre-27-ea.14_macos-aarch64_bin.tar.gz",
  "image_type": "jre",
  "java_version": "27-ea.14",
  "jvm_impl": "hotspot",
  "md5": "c29dce50d645a8a4dca27eb452bc49e1",
  "os": "macosx",
  "release_info": {
    "IMPLEMENTOR": "SAP SE",
    "IMPLEMENTOR_VERSION": "SapMachine",
    "JAVA_RUNTIME_VERSION": "27-ea+14",
    "JAVA_VERSION": "27",
    "JAVA_VERSION_DATE": "2026-09-15",
    "LIBC": "default",
    "MODULES": "java.base java.compiler java.datatransfer java.xml java.prefs java.desktop java.instrument java.logging java.management java.security.sasl java.naming java.rmi java.management.rmi java.net.http java.scripting java.security.jgss java.transaction.xa java.sql java.sql.rowset java.xml.crypto java.se java.smartcardio jdk.accessibility jdk.internal.jvmstat jdk.attach jdk.charsets jdk.crypto.cryptoki jdk.dynalink jdk.internal.vm.ci jdk.graal.compiler jdk.graal.compiler.management jdk.httpserver jdk.incubator.vector jdk.jcmd jdk.jdwp.agent jdk.jfr jdk.localedata jdk.management jdk.management.agent jdk.management.jfr jdk.naming.dns jdk.naming.rmi jdk.net jdk.nio.mapmode jdk.sapext jdk.sctp jdk.security.auth jdk.security.jgss jdk.unsupported jdk.xml.dom jdk.zipfs",
    "OS_ARCH": "aarch64",
    "OS_NAME": "Darwin",
    "SOURCE": ".:git:edef2e8df892"
  },
  "release_type": "ea",
  "sha1": "23b1ed6cc6b3b48b0e4b1c66b10eca5c347125cd",
  "sha256": "7c65b5e9cd0ae25149750245778c5183a42d61d468797e45e2e5b73682bd3fe7",
  "sha512": "4aa129164a331538eda7f53431e4bd25116320d40cb0d147d8df21a13def01f0ada1aade00cf67fd421314ff50c5f4e518c5c9dc652f9b5657339fe1280eda37",
  "size": 47091133,
  "url": "https://github.com/SAP/SapMachine/releases/download/sapmachine-27%2B14/sapmachine-jre-27-ea.14_macos-aarch64_bin.tar.gz",
  "vendor": "sap",
  "version": "27-ea.14"
}