{
  "architecture": "x86_64",
  "distro": "sapmachine",
  "features": [],
  "file_type": "zip",
  "filename": "sapmachine-jre-17.0.4_windows-x64_bin.zip",
  "image_type": "jre",
  "java_version": "17.0.4",
  "jvm_impl": "hotspot",
  "md5": "cb39a913411b2b5c2aa3adca5042ad7b",
  "os": "windows",
  "release_info": {
    "IMPLEMENTOR": "SAP SE",
    "IMPLEMENTOR_VERSION": "SapMachine",
    "JAVA_VERSION": "17.0.4",
    "JAVA_VERSION_DATE": "2022-07-19",
    "LIBC": "default",
    "MODULES": "java.base java.compiler java.datatransfer java.xml java.prefs java.desktop java.instrument java.logging java.management java.security.sasl java.naming java.rmi java.management.rmi java.net.http java.scripting java.security.jgss java.transaction.xa java.sql java.sql.rowset java.xml.crypto java.se java.smartcardio jdk.accessibility jdk.internal.jvmstat jdk.attach jdk.charsets jdk.crypto.ec jdk.crypto.cryptoki jdk.crypto.mscapi jdk.dynalink jdk.httpserver jdk.incubator.foreign jdk.incubator.vector jdk.internal.vm.ci jdk.internal.vm.compiler jdk.internal.vm.compiler.management jdk.jcmd jdk.jdwp.agent jdk.jfr jdk.jsobject jdk.localedata jdk.management jdk.management.agent jdk.management.jfr jdk.naming.dns jdk.naming.rmi jdk.net jdk.nio.mapmode jdk.sctp jdk.security.auth jdk.security.jgss jdk.unsupported jdk.xml.dom jdk.zipfs",
    "OS_ARCH": "x86_64",
    "OS_NAME": "Windows",
    "SOURCE": ".:git:6fc0ebf5d0bb"
  },
  "release_type": "ga",
  "sha1": "5040c1220baa04c9cadccd5073ac2f7d0edd639e",
  "sha256": "512f226b8680e26915a1e0d7c8a44297b545edefb8806d685c813bef671623d6",
  "sha512": "0ca4a167e58f0c714007bf7d8e1011633066c430a8b14664b4d537cccc6c711d1a218f85e0fd65b025e6c5dc364d21ff56ee213dce8b5e8b4a51dd2b33a1ef20",
  "size": 46935068,
  "url": "https://github.com/SAP/SapMachine/releases/download/sapmachine-17.0.4/sapmachine-jre-17.0.4_windows-x64_bin.zip",
  "vendor": "sap",
  "version": "17.0.4"
}