{
  "architecture": "aarch64",
  "distro": "jetbrains",
  "features": [],
  "file_type": "tar.gz",
  "filename": "jbr-25.0.3-linux-aarch64-b508.16.tar.gz",
  "image_type": "jre",
  "java_version": "25.0.3",
  "jvm_impl": "hotspot",
  "md5": "0a2290b85036184f0d5aeb5491d213fb",
  "os": "linux",
  "release_info": {
    "IMPLEMENTOR": "JetBrains s.r.o.",
    "IMPLEMENTOR_VERSION": "JBR-25.0.3+9-508.16-nomod",
    "JAVA_RUNTIME_VERSION": "25.0.3+9-b508.16",
    "JAVA_VERSION": "25.0.3",
    "LIBC": "gnu",
    "MODULES": "java.base java.compiler java.datatransfer java.xml java.prefs java.desktop java.instrument java.logging java.management java.security.sasl java.naming java.rmi java.management.rmi java.net.http java.scripting java.security.jgss java.transaction.xa java.sql java.sql.rowset java.xml.crypto java.se java.smartcardio jdk.accessibility jdk.internal.jvmstat jdk.attach jdk.charsets jdk.internal.opt jdk.zipfs jdk.compiler jdk.crypto.cryptoki jdk.crypto.ec jdk.dynalink jdk.hotspot.agent jdk.httpserver jdk.internal.ed jdk.internal.le jdk.internal.md jdk.internal.vm.ci jdk.javadoc jdk.jcmd jdk.jdwp.agent jdk.jdi jdk.jfr jdk.localedata jdk.management jdk.management.agent jdk.management.jfr jdk.naming.dns jdk.naming.rmi jdk.net jdk.sctp jdk.security.auth jdk.security.jgss jdk.unsupported jdk.unsupported.desktop jdk.xml.dom",
    "OS_ARCH": "aarch64",
    "OS_NAME": "Linux",
    "SOURCE": ".:git:c624f1bd9587+"
  },
  "release_type": "ga",
  "sha1": "4d500f32e775f35791f46d933ac62df52c31d7b2",
  "sha256": "8704ffff0723bbe00992a02e455cda6a76697b40f9a5b833fc853e3c3b05dd14",
  "sha512": "038cce6e7e2d68a28c1b269aff199c2e8a4bca58e24d27f9345fbb6031d6b6dc82d79d524586f3e96952d0272d2ca02fa84817df69b4f6052e9f2c5d34c02bad",
  "size": 103384696,
  "url": "https://cache-redirector.jetbrains.com/intellij-jbr/jbr-25.0.3-linux-aarch64-b508.16.tar.gz",
  "vendor": "jetbrains",
  "version": "25.0.3b508.16"
}