{"vendor":"jetbrains","filename":"jbr_jcef-17.0.3-windows-x64-b469.19.tar.gz","release_type":"ga","version":"17.0.3b469.19","java_version":"17.0.3","jvm_impl":"hotspot","os":"windows","architecture":"x86_64","file_type":"tar.gz","image_type":"jre","features":["jcef"],"url":"https://cache-redirector.jetbrains.com/intellij-jbr/jbr_jcef-17.0.3-windows-x64-b469.19.tar.gz","md5":"3e57d4c3b0798a35ca2f69045db9d374","md5_file":"jbr_jcef-17.0.3-windows-x64-b469.19.tar.gz.md5","sha1":"bb4c57cd6eead00b62b25b5becf71f4551e65590","sha1_file":"jbr_jcef-17.0.3-windows-x64-b469.19.tar.gz.sha1","sha256":"583eec922afd714cbc33c4deee2395db4f40b3b31ee2b5749efb75b7406c188d","sha256_file":"jbr_jcef-17.0.3-windows-x64-b469.19.tar.gz.sha256","sha512":"4bddc64ebde9ab82911403a1a5987f10f21b4c3918c2be9ba4e2f2939f63c7f524ab069c2eb4784e78ebb9f827e6ae4bbf2124db18ba77c4aecce3c490cd9681","sha512_file":"jbr_jcef-17.0.3-windows-x64-b469.19.tar.gz.sha512","size":176708490,"release_info":{}}
